{"status":"success","data":{"abstentions":"60","pourcent_blancs_ins":"5.84","pourcent_nuls_ins":"1.30","pourcent_exp_vot":"88.30","votants":"94","pourcent_exp_ins":"53.90","blancs":"9","resultats":[{"pourcent_voix_exp":"67.47","voix":"56","binome":"Mme ITTELET Isabelle et M. VERZELEN Pierre-Jean","pourcent_voix_ins":"36.36","code_nuance":"BC-UD","numero_panneau":"1"},{"pourcent_voix_exp":"32.53","voix":"27","binome":"M. DUMAND Romain et Mme PARFAIT Marie-Jeanne","pourcent_voix_ins":"17.53","code_nuance":"BC-FN","numero_panneau":"2"}],"code":"02096","pourcent_nuls_vot":"2.13","lib":"Bois-lès-Pargny","pourcent_blancs_vot":"9.57","nuls":"2","exprimes":"83","pourcent_vot_ins":"61.04","inscrits":"154","pourcent_abs_ins":"38.96"}}