{"status":"success","data":{"abstentions":"37233","pourcent_nuls_ins":"1.19","pourcent_blancs_ins":"3.62","pourcent_exp_vot":"91.11","votants":"43907","pourcent_exp_ins":"49.30","code_dep":"02","blancs":"2941","resultats":[{"pourcent_voix_exp":"25.05","voix":"10023","pourcent_voix_ins":"12.35","code_nuance":"BC-UG"},{"pourcent_voix_exp":"26.31","voix":"10527","pourcent_voix_ins":"12.97","code_nuance":"BC-UMP"},{"pourcent_voix_exp":".90","voix":"360","pourcent_voix_ins":".44","code_nuance":"BC-UD"},{"pourcent_voix_exp":"47.73","voix":"19094","pourcent_voix_ins":"23.53","code_nuance":"BC-FN"}],"pourcent_nuls_vot":"2.19","code_circo":"005","pourcent_blancs_vot":"6.70","nuls":"962","exprimes":"40004","pourcent_vot_ins":"54.11","inscrits":"81140","pourcent_abs_ins":"45.89","lib_circo":"5ème circonscription","lib_dep":"AISNE"}}