{"status":"success","data":{"abstentions":"47","pourcent_blancs_ins":"2.00","pourcent_nuls_ins":"3.20","pourcent_exp_vot":"93.60","votants":"203","pourcent_exp_ins":"76.00","blancs":"5","resultats":[{"pourcent_voix_exp":"70.53","voix":"134","binome":"M. ARRIUBERGE Jean et Mme CAMBON Valérie","pourcent_voix_ins":"53.60","code_nuance":"BC-DVG","numero_panneau":"3"},{"pourcent_voix_exp":"29.47","voix":"56","binome":"M. CANTON Marc et Mme YRONDI Béatrice","pourcent_voix_ins":"22.40","code_nuance":"BC-UD","numero_panneau":"4"}],"code":"64257","pourcent_nuls_vot":"3.94","lib":"Haut-de-Bosdarros","pourcent_blancs_vot":"2.46","nuls":"8","exprimes":"190","pourcent_vot_ins":"81.20","inscrits":"250","pourcent_abs_ins":"18.80"}}