{"status":"success","data":{"abstentions":"13432","pourcent_exp_vot":"98.49","votants":"52919","pourcent_blancs_nuls_vot":"1.51","pourcent_exp_ins":"78.55","code_dep":"78","resultats":[{"prenom":"Eva","pourcent_voix_exp":"2.49","voix":"1300","sexe":"F","pourcent_voix_ins":"1.96","code_nuance":"BC-CEC","nom":"JOLY"},{"prenom":"Marine","pourcent_voix_exp":"11.95","voix":"6226","sexe":"F","pourcent_voix_ins":"9.38","code_nuance":"BC-FN","nom":"LE PEN"},{"prenom":"Nicolas","pourcent_voix_exp":"32.53","voix":"16954","sexe":"M","pourcent_voix_ins":"25.55","code_nuance":"BC-UMP","nom":"SARKOZY"},{"prenom":"Jean-Luc","pourcent_voix_exp":"9.21","voix":"4800","sexe":"M","pourcent_voix_ins":"7.23","code_nuance":"BC-UG","nom":"MÉLENCHON"},{"prenom":"Philippe","pourcent_voix_exp":".89","voix":"466","sexe":"M","pourcent_voix_ins":".70","code_nuance":"BC-RDG","nom":"POUTOU"},{"prenom":"Nathalie","pourcent_voix_exp":".33","voix":"170","sexe":"F","pourcent_voix_ins":".26","code_nuance":"BC-RDG","nom":"ARTHAUD"},{"prenom":"Jacques","pourcent_voix_exp":".26","voix":"135","sexe":"M","pourcent_voix_ins":".20","code_nuance":"BC-DVG","nom":"CHEMINADE"},{"prenom":"François","pourcent_voix_exp":"11.33","voix":"5904","sexe":"M","pourcent_voix_ins":"8.90","code_nuance":"BC-MDM","nom":"BAYROU"},{"prenom":"Nicolas","pourcent_voix_exp":"1.85","voix":"962","sexe":"M","pourcent_voix_ins":"1.45","code_nuance":"BC-DVD","nom":"DUPONT-AIGNAN"},{"prenom":"François","pourcent_voix_exp":"29.17","voix":"15204","sexe":"M","pourcent_voix_ins":"22.91","code_nuance":"BC-SOC","nom":"HOLLANDE"}],"pourcent_blancs_nuls_ins":"1.20","code_circo":"012","exprimes":"52121","pourcent_vot_ins":"79.76","blancs_nuls":"798","inscrits":"66351","pourcent_abs_ins":"20.24","lib_circo":"12ème circonscription","lib_dep":"YVELINES"}}