{"status":"success","data":{"abstentions":"91","pourcent_blancs_ins":"4.98","pourcent_nuls_ins":"2.99","pourcent_exp_vot":"85.45","votants":"110","pourcent_exp_ins":"46.77","blancs":"10","resultats":[{"pourcent_voix_exp":"41.49","voix":"39","binome":"M. THOMAS Thierry et Mme WALTON Monique","pourcent_voix_ins":"19.40","code_nuance":"BC-SOC","numero_panneau":"2"},{"pourcent_voix_exp":"58.51","voix":"55","binome":"M. POLLET Armand et Mme SAILLARD Marion","pourcent_voix_ins":"27.36","code_nuance":"BC-FN","numero_panneau":"1"}],"code":"02366","pourcent_nuls_vot":"5.45","lib":"Hannapes","pourcent_blancs_vot":"9.09","nuls":"6","exprimes":"94","pourcent_vot_ins":"54.73","inscrits":"201","pourcent_abs_ins":"45.27"}}