{"status":"success","data":{"abstentions":"95","pourcent_blancs_ins":"7.45","pourcent_nuls_ins":"1.06","pourcent_exp_vot":"82.80","votants":"93","pourcent_exp_ins":"40.96","blancs":"14","resultats":[{"pourcent_voix_exp":"40.26","voix":"31","binome":"Mme PARENT Anne et M. THOMAS Denis","pourcent_voix_ins":"16.49","code_nuance":"BC-UD","numero_panneau":"1"},{"pourcent_voix_exp":"59.74","voix":"46","binome":"M. CHOUET Noël et Mme DAVID Cindy","pourcent_voix_ins":"24.47","code_nuance":"BC-FN","numero_panneau":"4"}],"code":"21236","pourcent_nuls_vot":"2.15","lib":"Ebaty","pourcent_blancs_vot":"15.05","nuls":"2","exprimes":"77","pourcent_vot_ins":"49.47","inscrits":"188","pourcent_abs_ins":"50.53"}}