{"status":"success","data":{"abstentions":"137","pourcent_blancs_ins":"3.07","pourcent_nuls_ins":"2.45","pourcent_exp_vot":"90.48","votants":"189","pourcent_exp_ins":"52.45","blancs":"10","resultats":[{"pourcent_voix_exp":"42.11","voix":"72","binome":"M. ARMARY Louis et Mme ROBIN-RODRIGO Chantal","pourcent_voix_ins":"22.09","code_nuance":"BC-RDG","numero_panneau":"3"},{"pourcent_voix_exp":"57.89","voix":"99","binome":"M. BEHAGUE Jacques et Mme BOILEAU Laurence","pourcent_voix_ins":"30.37","code_nuance":"BC-UD","numero_panneau":"1"}],"code":"65168","pourcent_nuls_vot":"4.23","lib":"Esquièze-Sère","pourcent_blancs_vot":"5.29","nuls":"8","exprimes":"171","pourcent_vot_ins":"57.98","inscrits":"326","pourcent_abs_ins":"42.02"}}