{"status":"success","data":{"abstentions":"257","pourcent_blancs_ins":"1.85","pourcent_nuls_ins":".31","pourcent_exp_vot":"96.41","votants":"390","pourcent_exp_ins":"58.11","blancs":"12","resultats":[{"pourcent_voix_exp":"67.82","voix":"255","binome":"M. COUREL Francis et Mme HAKI Marie-Claire","pourcent_voix_ins":"39.41","code_nuance":"BC-UG","numero_panneau":"3"},{"pourcent_voix_exp":"14.10","voix":"53","binome":"Mme DUONG Isabelle et M. JOILLE Christophe","pourcent_voix_ins":"8.19","code_nuance":"BC-UD","numero_panneau":"2"},{"pourcent_voix_exp":"18.09","voix":"68","binome":"M. HOUSSIN Timothée et Mme PIEL Alexandra","pourcent_voix_ins":"10.51","code_nuance":"BC-FN","numero_panneau":"1"}],"code":"27587","pourcent_nuls_vot":".51","lib":"Saint-Philbert-sur-Risle","pourcent_blancs_vot":"3.08","nuls":"2","exprimes":"376","pourcent_vot_ins":"60.28","inscrits":"647","pourcent_abs_ins":"39.72"}}