{"status":"success","data":{"abstentions":"147","pourcent_blancs_ins":"1.34","pourcent_nuls_ins":".34","pourcent_exp_vot":"96.69","votants":"151","pourcent_exp_ins":"48.99","blancs":"4","resultats":[{"pourcent_voix_exp":"37.67","voix":"55","binome":"Mme DIEZ-RICHER Elisabeth et M. OLLIVIER Michel","pourcent_voix_ins":"18.46","code_nuance":"BC-SOC","numero_panneau":"2"},{"pourcent_voix_exp":"23.29","voix":"34","binome":"Mme ROKVAM Brigitte et M. SAVIN Francis","pourcent_voix_ins":"11.41","code_nuance":"BC-UD","numero_panneau":"3"},{"pourcent_voix_exp":"39.04","voix":"57","binome":"M. CAPPELAERE Xavier et Mme CEYRAT Pascale","pourcent_voix_ins":"19.13","code_nuance":"BC-FN","numero_panneau":"1"}],"code":"17081","pourcent_nuls_vot":".66","lib":"Chamouillac","pourcent_blancs_vot":"2.65","nuls":"1","exprimes":"146","pourcent_vot_ins":"50.67","inscrits":"298","pourcent_abs_ins":"49.33"}}