{"status":"success","data":{"abstentions":"1678","pourcent_blancs_ins":"1.89","pourcent_nuls_ins":"1.04","pourcent_exp_vot":"94.57","votants":"1972","pourcent_exp_ins":"51.10","blancs":"69","resultats":[{"pourcent_voix_exp":"71.21","voix":"1328","binome":"Mme ALFANO Alfonsa et M. SUBLON Yves","pourcent_voix_ins":"36.38","code_nuance":"BC-UMP","numero_panneau":"6"},{"pourcent_voix_exp":"28.79","voix":"537","binome":"M. JACQUEMIN Valerian et Mme TINOT Brigitte","pourcent_voix_ins":"14.71","code_nuance":"BC-FN","numero_panneau":"3"}],"code":"67131","pourcent_nuls_vot":"1.93","lib":"Eschau","pourcent_blancs_vot":"3.50","nuls":"38","exprimes":"1865","pourcent_vot_ins":"54.03","inscrits":"3650","pourcent_abs_ins":"45.97"}}