{"status":"success","data":{"abstentions":"479","pourcent_blancs_ins":"1.21","pourcent_nuls_ins":".95","pourcent_exp_vot":"96.31","votants":"677","pourcent_exp_ins":"56.40","blancs":"14","resultats":[{"pourcent_voix_exp":"36.66","voix":"239","binome":"Mme GARCIN SAUDO Julie et M. GAUDY Vincent","pourcent_voix_ins":"20.67","code_nuance":"BC-SOC","numero_panneau":"4"},{"pourcent_voix_exp":"22.85","voix":"149","binome":"M. DUFFOUR Gérard et Mme SANCHEZ-D'ETTORE Géraldine","pourcent_voix_ins":"12.89","code_nuance":"BC-UD","numero_panneau":"5"},{"pourcent_voix_exp":"40.49","voix":"264","binome":"M. ARNAL Vincent et Mme DESPOTS Patricia","pourcent_voix_ins":"22.84","code_nuance":"BC-FN","numero_panneau":"3"}],"code":"34325","pourcent_nuls_vot":"1.62","lib":"Valros","pourcent_blancs_vot":"2.07","nuls":"11","exprimes":"652","pourcent_vot_ins":"58.56","inscrits":"1156","pourcent_abs_ins":"41.44"}}