{"status":"success","data":{"abstentions":"121","pourcent_blancs_ins":"3.69","pourcent_nuls_ins":".74","pourcent_exp_vot":"92.00","votants":"150","pourcent_exp_ins":"50.92","blancs":"10","resultats":[{"pourcent_voix_exp":"65.94","voix":"91","binome":"Mme LABADENS Sylvie et M. SIEGLER Nicolas","pourcent_voix_ins":"33.58","code_nuance":"BC-UD","numero_panneau":"1"},{"pourcent_voix_exp":"34.06","voix":"47","binome":"M. BASQUIN Thierry et Mme LEMAIRE Louise-Marie","pourcent_voix_ins":"17.34","code_nuance":"BC-FN","numero_panneau":"3"}],"code":"59085","pourcent_nuls_vot":"1.33","lib":"Blécourt","pourcent_blancs_vot":"6.67","nuls":"2","exprimes":"138","pourcent_vot_ins":"55.35","inscrits":"271","pourcent_abs_ins":"44.65"}}