{"status":"success","data":{"abstentions":"1756","pourcent_blancs_ins":"1.62","pourcent_nuls_ins":".40","pourcent_exp_vot":"95.65","votants":"1516","pourcent_exp_ins":"44.32","blancs":"53","resultats":[{"pourcent_voix_exp":"63.93","voix":"927","binome":"Mme PIERRARD Nicole et M. REICHHELD Patrick","pourcent_voix_ins":"28.33","code_nuance":"BC-DVD","numero_panneau":"2"},{"pourcent_voix_exp":"36.07","voix":"523","binome":"Mme GAZAUD Camille et M. SINTEFF Alexandre","pourcent_voix_ins":"15.98","code_nuance":"BC-FN","numero_panneau":"1"}],"code":"57540","pourcent_nuls_vot":".86","lib":"Phalsbourg","pourcent_blancs_vot":"3.50","nuls":"13","exprimes":"1450","pourcent_vot_ins":"46.33","inscrits":"3272","pourcent_abs_ins":"53.67"}}