{"status":"success","data":{"abstentions":"227","pourcent_blancs_ins":"3.48","pourcent_nuls_ins":"1.02","pourcent_exp_vot":"91.60","votants":"262","pourcent_exp_ins":"49.08","blancs":"17","resultats":[{"pourcent_voix_exp":"27.50","voix":"66","binome":"Mme PELTRE Martine et M. ZIEGER Camille","pourcent_voix_ins":"13.50","code_nuance":"BC-UMP","numero_panneau":"3"},{"pourcent_voix_exp":"30.83","voix":"74","binome":"Mme HERZOG Christine et M. SIMON Bernard","pourcent_voix_ins":"15.13","code_nuance":"BC-DVD","numero_panneau":"1"},{"pourcent_voix_exp":"41.67","voix":"100","binome":"Mme MALASSE Nadine et M. PIERRE Stéphane","pourcent_voix_ins":"20.45","code_nuance":"BC-FN","numero_panneau":"2"}],"code":"57564","pourcent_nuls_vot":"1.91","lib":"Réchicourt-le-Château","pourcent_blancs_vot":"6.49","nuls":"5","exprimes":"240","pourcent_vot_ins":"53.58","inscrits":"489","pourcent_abs_ins":"46.42"}}