{"status":"success","data":{"abstentions":"96","pourcent_blancs_ins":"3.75","pourcent_nuls_ins":"5.24","pourcent_exp_vot":"85.96","votants":"171","pourcent_exp_ins":"55.06","blancs":"10","resultats":[{"pourcent_voix_exp":"53.06","voix":"78","binome":"Mme ALARY Marielle et M. PAGEOT Jean-Philippe","pourcent_voix_ins":"29.21","code_nuance":"BC-SOC","numero_panneau":"2"},{"pourcent_voix_exp":"46.94","voix":"69","binome":"M. DELRIEU Christian et Mme FOURNIER-BOURGEADE Michèle","pourcent_voix_ins":"25.84","code_nuance":"BC-DVD","numero_panneau":"1"}],"code":"46283","pourcent_nuls_vot":"8.19","lib":"Saint-Michel-de-Bannières","pourcent_blancs_vot":"5.85","nuls":"14","exprimes":"147","pourcent_vot_ins":"64.04","inscrits":"267","pourcent_abs_ins":"35.96"}}