{"status":"success","data":{"abstentions":"103","pourcent_blancs_ins":"3.13","pourcent_nuls_ins":"1.88","pourcent_exp_vot":"92.59","votants":"216","pourcent_exp_ins":"62.70","blancs":"10","resultats":[{"pourcent_voix_exp":"45.50","voix":"91","binome":"Mme BORGOO Martine et M. DECORDE Gérard","pourcent_voix_ins":"28.53","code_nuance":"BC-UD","numero_panneau":"1"},{"pourcent_voix_exp":"54.50","voix":"109","binome":"M. ADOUX Jean-Jacques et Mme HÉVIN Colette","pourcent_voix_ins":"34.17","code_nuance":"BC-FN","numero_panneau":"3"}],"code":"60288","pourcent_nuls_vot":"2.78","lib":"Grémévillers","pourcent_blancs_vot":"4.63","nuls":"6","exprimes":"200","pourcent_vot_ins":"67.71","inscrits":"319","pourcent_abs_ins":"32.29"}}