{"status":"success","data":{"abstentions":"47","pourcent_blancs_ins":"6.31","pourcent_nuls_ins":"6.31","pourcent_exp_vot":"78.13","votants":"64","pourcent_exp_ins":"45.05","blancs":"7","resultats":[{"pourcent_voix_exp":"54.00","voix":"27","binome":"M. RAYMONDAUD Yves et Mme REJASSE Jocelyne","pourcent_voix_ins":"24.32","code_nuance":"BC-SOC","numero_panneau":"1"},{"pourcent_voix_exp":"46.00","voix":"23","binome":"M. DESCUBES Bruno et Mme SAUGET Dominique","pourcent_voix_ins":"20.72","code_nuance":"BC-DVD","numero_panneau":"4"}],"code":"87137","pourcent_nuls_vot":"10.94","lib":"Saint-Bazile","pourcent_blancs_vot":"10.94","nuls":"7","exprimes":"50","pourcent_vot_ins":"57.66","inscrits":"111","pourcent_abs_ins":"42.34"}}