{"status":"success","data":{"abstentions":"195","pourcent_blancs_ins":"5.65","pourcent_nuls_ins":".47","pourcent_exp_vot":"88.70","votants":"230","pourcent_exp_ins":"48.00","blancs":"24","resultats":[{"pourcent_voix_exp":"66.18","voix":"135","binome":"M. LORNE Fabien et Mme PAINEAU Catherine","pourcent_voix_ins":"31.76","code_nuance":"BC-UD","numero_panneau":"3"},{"pourcent_voix_exp":"33.82","voix":"69","binome":"Mme BOUQUET Esméralda et M. LE PENNEC Guy","pourcent_voix_ins":"16.24","code_nuance":"BC-FN","numero_panneau":"4"}],"code":"72216","pourcent_nuls_vot":".87","lib":"Neuvillalais","pourcent_blancs_vot":"10.43","nuls":"2","exprimes":"204","pourcent_vot_ins":"54.12","inscrits":"425","pourcent_abs_ins":"45.88"}}