{"status":"success","data":{"abstentions":"20","pourcent_blancs_ins":"7.55","pourcent_nuls_ins":"5.66","pourcent_exp_vot":"78.79","votants":"33","pourcent_exp_ins":"49.06","blancs":"4","resultats":[{"pourcent_voix_exp":"57.69","voix":"15","binome":"Mme SCHOLLHAMMER Fabienne et M. SIDO Bruno","pourcent_voix_ins":"28.30","code_nuance":"BC-UMP","numero_panneau":"4"},{"pourcent_voix_exp":"42.31","voix":"11","binome":"M. CRESSELY David et Mme THOMAS Fanny","pourcent_voix_ins":"20.75","code_nuance":"BC-FN","numero_panneau":"1"}],"code":"52304","pourcent_nuls_vot":"9.09","lib":"Malaincourt-sur-Meuse","pourcent_blancs_vot":"12.12","nuls":"3","exprimes":"26","pourcent_vot_ins":"62.26","inscrits":"53","pourcent_abs_ins":"37.74"}}