{"status":"success","data":{"abstentions":"4827","pourcent_blancs_ins":"3.03","pourcent_nuls_ins":"1.01","pourcent_exp_vot":"91.35","votants":"4221","pourcent_exp_ins":"42.62","blancs":"274","resultats":[{"pourcent_voix_exp":"65.25","voix":"2516","binome":"M. LAMIRAY David et Mme MANZANARES Brigitte","pourcent_voix_ins":"27.81","code_nuance":"BC-SOC","numero_panneau":"5"},{"pourcent_voix_exp":"34.75","voix":"1340","binome":"M. ODIEVRE Julien et Mme QUENNEVILLE Véronique","pourcent_voix_ins":"14.81","code_nuance":"BC-FN","numero_panneau":"4"}],"code":"76157","pourcent_nuls_vot":"2.16","lib":"Canteleu","pourcent_blancs_vot":"6.49","nuls":"91","exprimes":"3856","pourcent_vot_ins":"46.65","inscrits":"9048","pourcent_abs_ins":"53.35"}}