{"status":"success","data":{"abstentions":"241","pourcent_blancs_ins":"4.12","pourcent_nuls_ins":".65","pourcent_exp_vot":"90.00","votants":"220","pourcent_exp_ins":"42.95","blancs":"19","resultats":[{"pourcent_voix_exp":"42.93","voix":"85","binome":"M. JEANNE Patrick et Mme THEVENOT Maryse","pourcent_voix_ins":"18.44","code_nuance":"BC-UG","numero_panneau":"4"},{"pourcent_voix_exp":"57.07","voix":"113","binome":"M. BAZILLE Alain et Mme TESSIER Dominique","pourcent_voix_ins":"24.51","code_nuance":"BC-UD","numero_panneau":"2"}],"code":"76706","pourcent_nuls_vot":"1.36","lib":"Tourville-les-Ifs","pourcent_blancs_vot":"8.64","nuls":"3","exprimes":"198","pourcent_vot_ins":"47.72","inscrits":"461","pourcent_abs_ins":"52.28"}}