{"status":"success","data":{"abstentions":"12878","pourcent_exp_vot":"97.83","votants":"69498","pourcent_blancs_nuls_vot":"2.17","pourcent_exp_ins":"82.54","code_dep":"41","resultats":[{"prenom":"Eva","pourcent_voix_exp":"1.63","voix":"1108","sexe":"F","pourcent_voix_ins":"1.35","code_nuance":"BC-CEC","nom":"JOLY"},{"prenom":"Marine","pourcent_voix_exp":"21.16","voix":"14386","sexe":"F","pourcent_voix_ins":"17.46","code_nuance":"BC-FN","nom":"LE PEN"},{"prenom":"Nicolas","pourcent_voix_exp":"28.91","voix":"19658","sexe":"M","pourcent_voix_ins":"23.86","code_nuance":"BC-UMP","nom":"SARKOZY"},{"prenom":"Jean-Luc","pourcent_voix_exp":"9.51","voix":"6464","sexe":"M","pourcent_voix_ins":"7.85","code_nuance":"BC-UG","nom":"MÉLENCHON"},{"prenom":"Philippe","pourcent_voix_exp":"1.44","voix":"977","sexe":"M","pourcent_voix_ins":"1.19","code_nuance":"BC-RDG","nom":"POUTOU"},{"prenom":"Nathalie","pourcent_voix_exp":".82","voix":"557","sexe":"F","pourcent_voix_ins":".68","code_nuance":"BC-RDG","nom":"ARTHAUD"},{"prenom":"Jacques","pourcent_voix_exp":".26","voix":"180","sexe":"M","pourcent_voix_ins":".22","code_nuance":"BC-DVG","nom":"CHEMINADE"},{"prenom":"François","pourcent_voix_exp":"10.26","voix":"6974","sexe":"M","pourcent_voix_ins":"8.47","code_nuance":"BC-MDM","nom":"BAYROU"},{"prenom":"Nicolas","pourcent_voix_exp":"2.26","voix":"1538","sexe":"M","pourcent_voix_ins":"1.87","code_nuance":"BC-DVD","nom":"DUPONT-AIGNAN"},{"prenom":"François","pourcent_voix_exp":"23.75","voix":"16151","sexe":"M","pourcent_voix_ins":"19.61","code_nuance":"BC-SOC","nom":"HOLLANDE"}],"pourcent_blancs_nuls_ins":"1.83","code_circo":"003","exprimes":"67993","pourcent_vot_ins":"84.37","blancs_nuls":"1505","inscrits":"82376","pourcent_abs_ins":"15.63","lib_circo":"3ème circonscription","lib_dep":"LOIR ET CHER"}}