{"status":"success","data":{"abstentions":"1730","pourcent_blancs_ins":"1.43","pourcent_nuls_ins":".73","pourcent_exp_vot":"95.65","votants":"1701","pourcent_exp_ins":"47.42","blancs":"49","resultats":[{"pourcent_voix_exp":"31.90","voix":"519","binome":"Mme COURDAVAULT Arlette et M. PROUST Eric","pourcent_voix_ins":"15.13","code_nuance":"BC-DVG","numero_panneau":"4"},{"pourcent_voix_exp":"68.10","voix":"1108","binome":"M. PARENT Michel et Mme RABELLE Dominique","pourcent_voix_ins":"32.29","code_nuance":"BC-UMP","numero_panneau":"1"}],"code":"17093","pourcent_nuls_vot":"1.47","lib":"Le Château-d'Oléron","pourcent_blancs_vot":"2.88","nuls":"25","exprimes":"1627","pourcent_vot_ins":"49.58","inscrits":"3431","pourcent_abs_ins":"50.42"}}