{"status":"success","data":{"abstentions":"89","pourcent_blancs_ins":"1.79","pourcent_nuls_ins":"1.79","pourcent_exp_vot":"92.41","votants":"79","pourcent_exp_ins":"43.45","blancs":"3","resultats":[{"pourcent_voix_exp":"54.79","voix":"40","binome":"Mme GADY DUQUESNE Patricia et M. RICHARD Jean-Pierre","pourcent_voix_ins":"23.81","code_nuance":"BC-UD","numero_panneau":"2"},{"pourcent_voix_exp":"45.21","voix":"33","binome":"M. CHAPRON Philippe et Mme LINARÈS Sandrine","pourcent_voix_ins":"19.64","code_nuance":"BC-FN","numero_panneau":"4"}],"code":"14716","pourcent_nuls_vot":"3.80","lib":"Trungy","pourcent_blancs_vot":"3.80","nuls":"3","exprimes":"73","pourcent_vot_ins":"47.02","inscrits":"168","pourcent_abs_ins":"52.98"}}