{"status":"success","data":{"abstentions":"56","pourcent_blancs_ins":".88","pourcent_nuls_ins":"1.75","pourcent_exp_vot":"94.83","votants":"58","pourcent_exp_ins":"48.25","blancs":"1","resultats":[{"pourcent_voix_exp":"58.18","voix":"32","binome":"Mme HIVER Christelle et M. SOMON Laurent","pourcent_voix_ins":"28.07","code_nuance":"BC-UMP","numero_panneau":"3"},{"pourcent_voix_exp":"41.82","voix":"23","binome":"M. DE FRANCQUEVILLE Etienne et Mme DE LA ROCHÈRE Amélie","pourcent_voix_ins":"20.18","code_nuance":"BC-FN","numero_panneau":"1"}],"code":"80440","pourcent_nuls_vot":"3.45","lib":"Hiermont","pourcent_blancs_vot":"1.72","nuls":"2","exprimes":"55","pourcent_vot_ins":"50.88","inscrits":"114","pourcent_abs_ins":"49.12"}}